h2ssscam/BaseCalc.py
h2ssscam/Constants.py
h2ssscam/__init__.py
h2ssscam/__main__.py
h2ssscam/create_config_file.py
h2ssscam/data_loader.py
h2ssscam/plotting_funcs.py
h2ssscam/data/__init__.py
h2ssscam/data/config.ini
h2ssscam/data/h2fluor_data_Abgrall+1993.npz
h2ssscam/data/hi_data_NIST.npz
h2ssscam-0.2.6.dist-info/licenses/LICENSE
h2ssscam-0.2.6.dist-info/METADATA
h2ssscam-0.2.6.dist-info/WHEEL
h2ssscam-0.2.6.dist-info/entry_points.txt
h2ssscam-0.2.6.dist-info/top_level.txt
h2ssscam-0.2.6.dist-info/RECORD
