Metadata-Version: 2.4
Name: h2ssscam
Version: 0.2.6
Summary: Synthetic H2 fluorescence code refactored by Cole Meyer, Daniel Lopez-Sanders, Cassandra S. Cruz, Dominik P. Pacholski during Code/Astro 2025. The code is based on  ''Empirically estimated far-UV extinction curves for classical T Tauri stars'', McJunkin, M., France, K., Schindhelm, R., Herczeg, G., Schneider, P. C., & Brown, A. (2016), ApJ, 828, 69.
Requires-Python: >=3.10
License-File: LICENSE
Requires-Dist: astropy==6.1.7
Requires-Dist: matplotlib==3.10.5
Requires-Dist: numpy==2.2.6
Requires-Dist: pyqt6>=6.9.1
Requires-Dist: scipy==1.15.3
Provides-Extra: docs
Requires-Dist: sphinx; extra == "docs"
Requires-Dist: sphinx_rtd_theme; extra == "docs"
Dynamic: license-file
